tensorflow_technical_indicators/__init__.py
tensorflow_technical_indicators/features.py
tensorflow_technical_indicators/macd.py
tensorflow_technical_indicators/moving_average.py
tensorflow_technical_indicators/rsi.py
tests/__init__.py
tests/features_test.py
tests/macd_test.py
tests/moving_average_test.py
tests/rsi_test.py
tensorflow_technical_indicators-0.1.2.dist-info/LICENSE.md
tensorflow_technical_indicators-0.1.2.dist-info/METADATA
tensorflow_technical_indicators-0.1.2.dist-info/WHEEL
tensorflow_technical_indicators-0.1.2.dist-info/top_level.txt
tensorflow_technical_indicators-0.1.2.dist-info/RECORD
