Metadata-Version: 2.1
Name: tensorflow-technical-indicators
Version: 0.1.2
Summary: Technical Indicators as TensorFlow Graph Functions
Home-page: https://github.com/ntakouris/tf-technical-indicators
Author: Theodoros Ntakouris
Author-email: zarkopafilis@gmail.com
License: UNKNOWN
Platform: UNKNOWN
Classifier: Development Status :: 4 - Beta
Classifier: Environment :: Console
Classifier: Programming Language :: Python :: 3
Classifier: License :: OSI Approved :: MIT License
Classifier: Operating System :: OS Independent
Requires-Python: >=3.6
